setup.py
miniquine/__init__.py
miniquine.egg-info/PKG-INFO
miniquine.egg-info/SOURCES.txt
miniquine.egg-info/dependency_links.txt
miniquine.egg-info/top_level.txt
quine/__init__.py