Metadata-Version: 1.1
Name: miniquine
Version: 1.0
Summary: A library to allow the shortest python quine: import quine
Home-page: UNKNOWN
Author: Benjamin Zagorsky
Author-email: bzagorsky at gmail.com
License: MIT
Keywords: quine
Platform: UNKNOWN
Classifier: License :: OSI Approved :: MIT License
Classifier: Operating System :: MacOS :: MacOS X
Classifier: Operating System :: Microsoft :: Windows
Classifier: Operating System :: POSIX
Classifier: Programming Language :: Python
